setup_server.py
client/__init__.py
client/client.py
client/client/__init__.py
client/client/add_contact.py
client/client/database.py
client/client/del_contact.py
client/client/main_window.py
client/client/main_window_conv.py
client/client/start_dialog.py
client/client/transport.py
client/common/__init__.py
client/common/decos.py
client/common/descriptors.py
client/common/errors.py
client/common/metaclasses.py
client/common/utils.py
client/common/variables.py
client/doc_11/__init__.py
client/doc_11/source/__init__.py
client/doc_11/source/conf.py
client/prj_log/__init__.py
client/prj_log/configs/__init__.py
client/prj_log/configs/config_client_log.py
client/prj_log/configs/config_server_log.py
client/unit_tests/__init__.py
client/unit_tests/test_client.py
client/unit_tests/test_server.py
client/unit_tests/test_utils.py
mess_server88.egg-info/PKG-INFO
mess_server88.egg-info/SOURCES.txt
mess_server88.egg-info/dependency_links.txt
mess_server88.egg-info/requires.txt
mess_server88.egg-info/top_level.txt
server/__init__.py
server/server.py
server/common/__init__.py
server/common/decos.py
server/common/descriptors.py
server/common/errors.py
server/common/metaclasses.py
server/common/utils.py
server/common/variables.py
server/doc_11/__init__.py
server/doc_11/source/__init__.py
server/doc_11/source/conf.py
server/prj_log/__init__.py
server/prj_log/configs/__init__.py
server/prj_log/configs/config_client_log.py
server/prj_log/configs/config_server_log.py
server/server/__init__.py
server/server/add_user.py
server/server/config_window.py
server/server/core.py
server/server/database.py
server/server/main_window.py
server/server/remove_user.py
server/server/stat_window.py
server/unit_tests/__init__.py
server/unit_tests/test_client.py
server/unit_tests/test_server.py
server/unit_tests/test_utils.py